fdroid_dl/__init__.py
fdroid_dl/__main__.py
fdroid_dl/download/__init__.py
fdroid_dl/download/futuressession.py
fdroid_dl/download/verifieddownload.py
fdroid_dl/json/__init__.py
fdroid_dl/json/encoder.py
fdroid_dl/model/__init__.py
fdroid_dl/model/appmetadata.py
fdroid_dl/model/config.py
fdroid_dl/model/index.py
fdroid_dl/model/metadata.py
fdroid_dl/model/repoconfig.py
fdroid_dl/processor/__init__.py
fdroid_dl/processor/index.py
fdroid_dl/update/__init__.py
fdroid_dl/update/apk.py
fdroid_dl/update/index.py
fdroid_dl/update/metadata.py
fdroid_dl/update/selector.py
fdroid_dl/update/src.py
fdroid_dl/update/update.py
test/__init__.py
test/test_config.py
fdroid_dl-0.1.0.dist-info/LICENSE
fdroid_dl-0.1.0.dist-info/METADATA
fdroid_dl-0.1.0.dist-info/WHEEL
fdroid_dl-0.1.0.dist-info/entry_points.txt
fdroid_dl-0.1.0.dist-info/top_level.txt
fdroid_dl-0.1.0.dist-info/RECORD
