Metadata-Version: 2.1
Name: fdroid-dl
Version: 0.1.0
Summary: fdroid-dl is a f-droid (offline) mirror generation and update utility
Home-page: https://github.com/t4skforce/fdroid-dl
Author: t4skforce
Author-email: 7422037+t4skforce@users.noreply.github.com
License: UNKNOWN
Platform: UNKNOWN
Classifier: Development Status :: 2 - Pre-Alpha
Classifier: Environment :: Console
Classifier: Programming Language :: Python :: 2.7
Classifier: Programming Language :: Python :: 3.5
Classifier: Programming Language :: Python :: 3.6
Classifier: Programming Language :: Python :: 3.7
Classifier: Programming Language :: Python :: 3.8
Classifier: Natural Language :: English
Classifier: License :: OSI Approved :: MIT License
Classifier: Operating System :: OS Independent
Requires-Python: >=2.7, !=3.0.*, !=3.1.*, !=3.2.*, !=3.3.*, <4
Requires-Dist: requests-futures (>=0.9.7)
Requires-Dist: PyYAML (>=3.13)
Requires-Dist: click (>=6.7)
